turbogpt/__init__.py
turbogpt/turbogpt.py
turbogpt_pro-1.1.1.dist-info/LICENSE
turbogpt_pro-1.1.1.dist-info/LICENSE.TXT
turbogpt_pro-1.1.1.dist-info/METADATA
turbogpt_pro-1.1.1.dist-info/WHEEL
turbogpt_pro-1.1.1.dist-info/top_level.txt
turbogpt_pro-1.1.1.dist-info/RECORD
