Metadata-Version: 2.1
Name: turbogpt_pro
Version: 1.1.1
Summary: A python based wrapper for GPT-4 & GPT-3.5 PLUS.
Author: yanjlee
Author-email: yanjlee@163.com
Classifier: Programming Language :: Python :: 3
Classifier: License :: OSI Approved :: MIT License
Classifier: Operating System :: OS Independent
Requires-Python: >=3.6
License-File: LICENSE
License-File: LICENSE.TXT
Requires-Dist: requests
Requires-Dist: faker
Requires-Dist: execjs
Requires-Dist: loguru
Requires-Dist: base64
Requires-Dist: hashlib
Requires-Dist: Crypto
Requires-Dist: pandas
Requires-Dist: fuzzywuzzy
Requires-Dist: httpx
Requires-Dist: Pillow
Requires-Dist: playwright
Requires-Dist: PyExecJS
Requires-Dist: redis
Requires-Dist: fastapi
Requires-Dist: uvicorn
Requires-Dist: APScheduler
Requires-Dist: beautifulsoup4
Requires-Dist: bs4
Requires-Dist: certifi
Requires-Dist: clickhouse-driver
Requires-Dist: curl-cffi
Requires-Dist: DrissionPage
Requires-Dist: fake-useragent
Requires-Dist: Flask
Requires-Dist: Flask-APScheduler
Requires-Dist: Flask-Cors
Requires-Dist: frida
Requires-Dist: gevent
Requires-Dist: Jinja2
Requires-Dist: langchain
Requires-Dist: langchain-community
Requires-Dist: suiutils-py
Requires-Dist: python-dotenv ==1.0.0
Requires-Dist: tls-client ==0.1.9
